tea/__init__.py
tea/tea.py
tea_python-1.1.data/data/README.md
tea_python-1.1.dist-info/LICENSE
tea_python-1.1.dist-info/METADATA
tea_python-1.1.dist-info/WHEEL
tea_python-1.1.dist-info/top_level.txt
tea_python-1.1.dist-info/RECORD
