Metadata-Version: 2.1
Name: tea-python
Version: 1.1
Summary: Tiny Encryption Algorithm
Home-page: https://github.com/luckpi/tea-python
Author: luckpi
Author-email: ojbk@live.com
Classifier: Programming Language :: Python :: 3
Classifier: License :: OSI Approved :: MIT License
Classifier: Operating System :: OS Independent
License-File: LICENSE
